[
  {
    "label": "中国",
    "value": 1,
    "children": [
      {
        "label": "北京市",
        "value": 2
      },
      {
        "label": "福建省",
        "value": 3,
        "children": [
          {
            "label": "福州市",
            "value": 36
          },
          {
            "label": "南平市",
            "value": 37
          },
          {
            "label": "泉州市",
            "value": 38
          },
          {
            "label": "莆田市",
            "value": 39
          }
        ]
      },
      {
        "label": "广东省",
        "value": 4,
        "children": [
          {
            "label": "广州市",
            "value": 45
          },
          {
            "label": "深圳市",
            "value": 46
          },
          {
            "label": "肇庆市",
            "value": 47
          },
          {
            "label": "惠州市",
            "value": 48
          },
          {
            "label": "阳江市",
            "value": 49
          },
          {
            "label": "茂名市",
            "value": 50
          },
          {
            "label": "湛江市",
            "value": 51
          },
          {
            "label": "中山市",
            "value": 52
          },
          {
            "label": "珠海市",
            "value": 53
          },
          {
            "label": "江门市",
            "value": 54
          }
        ]
      },
      {
        "label": "内蒙古自治区",
        "value": 5,
        "children": [
          {
            "label": "呼和浩特市",
            "value": 66
          },
          {
            "label": "赤峰市",
            "value": 67
          },
          {
            "label": "鄂尔多斯市",
            "value": 68
          },
          {
            "label": "乌兰察布市",
            "value": 69
          },
          {
            "label": "巴彦淖尔市",
            "value": 70
          }
        ]
      },
      {
        "label": "香港",
        "value": 6
      },
      {
        "label": "台湾",
        "value": 7
      },
      {
        "label": "贵州省",
        "value": 8,
        "children": [
          {
            "label": "贵阳市",
            "value": 78
          },
          {
            "label": "黔南布依族苗族自治州",
            "value": 79
          },
          {
            "label": "铜仁地区",
            "value": 80
          }
        ]
      },
      {
        "label": "宁夏回族自治区",
        "value": 9,
        "children": [
          {
            "label": "银川市",
            "value": 87
          }
        ]
      },
      {
        "label": "江苏省",
        "value": 11,
        "children": [
          {
            "label": "南京市",
            "value": 109
          },
          {
            "label": "常州市",
            "value": 110
          },
          {
            "label": "苏州市",
            "value": 111
          },
          {
            "label": "无锡市",
            "value": 112
          },
          {
            "label": "徐州市",
            "value": 113
          },
          {
            "label": "连云港市",
            "value": 114
          },
          {
            "label": "扬州市",
            "value": 115
          },
          {
            "label": "宿迁市",
            "value": 116
          },
          {
            "label": "淮安市",
            "value": 117
          },
          {
            "label": "泰州市",
            "value": 118
          },
          {
            "label": "南通市",
            "value": 119
          },
          {
            "label": "盐城市",
            "value": 120
          },
          {
            "label": "镇江市",
            "value": 121
          }
        ]
      },
      {
        "label": "澳门",
        "value": 20
      },
      {
        "label": "湖北省",
        "value": 21,
        "children": [
          {
            "label": "武汉市",
            "value": 214
          },
          {
            "label": "荆州市",
            "value": 215
          },
          {
            "label": "宜昌市",
            "value": 216
          },
          {
            "label": "襄樊市",
            "value": 217
          },
          {
            "label": "孝感市",
            "value": 218
          },
          {
            "label": "黄冈市",
            "value": 219
          },
          {
            "label": "黄石市",
            "value": 220
          },
          {
            "label": "咸宁市",
            "value": 221
          },
          {
            "label": "荆门市",
            "value": 222
          },
          {
            "label": "神农架林区",
            "value": 223
          },
          {
            "label": "鄂州市",
            "value": 224
          },
          {
            "label": "随州市",
            "value": 225
          },
          {
            "label": "恩施土家族苗族自治州",
            "value": 226
          },
          {
            "label": "十堰市",
            "value": 373
          }
        ]
      },
      {
        "label": "西藏自治区",
        "value": 22,
        "children": [
          {
            "label": "拉萨市",
            "value": 227
          },
          {
            "label": "日喀则地区",
            "value": 228
          },
          {
            "label": "山南地区",
            "value": 229
          },
          {
            "label": "林芝地区",
            "value": 230
          },
          {
            "label": "昌都地区",
            "value": 231
          },
          {
            "label": "那曲地区",
            "value": 232
          },
          {
            "label": "阿里地区",
            "value": 233
          }
        ]
      },
      {
        "label": "天津市",
        "value": 23
      },
      {
        "label": "上海市",
        "value": 24
      },
      {
        "label": "河北省",
        "value": 25,
        "children": [
          {
            "label": "石家庄市",
            "value": 234
          },
          {
            "label": "保定市",
            "value": 235
          },
          {
            "label": "邯郸市",
            "value": 236
          }
        ]
      },
      {
        "label": "甘肃省",
        "value": 26,
        "children": [
          {
            "label": "定西市",
            "value": 245
          },
          {
            "label": "天水市",
            "value": 246
          },
          {
            "label": "兰州市",
            "value": 247
          }
        ]
      },
      {
        "label": "浙江省",
        "value": 27,
        "children": [
          {
            "label": "杭州市",
            "value": 257
          },
          {
            "label": "金华市",
            "value": 258
          },
          {
            "label": "丽水市",
            "value": 259
          }
        ]
      },
      {
        "label": "吉林省",
        "value": 28,
        "children": [
          {
            "label": "长春市",
            "value": 268
          },
          {
            "label": "吉林市",
            "value": 269
          },
          {
            "label": "四平市",
            "value": 270
          }
        ]
      },
      {
        "label": "江西省",
        "value": 31,
        "children": [
          {
            "label": "南昌市",
            "value": 303
          },
          {
            "label": "九江市",
            "value": 304
          },
          {
            "label": "景德镇市",
            "value": 305
          }
        ]
      },
      {
        "label": "青海省",
        "value": 34,
        "children": [
          {
            "label": "西宁市",
            "value": 348
          },
          {
            "label": "海西蒙古族藏族自治州",
            "value": 349
          }
        ]
      },
      {
        "label": "海南省",
        "value": 35,
        "children": [
          {
            "label": "三亚市",
            "value": 356
          },
          {
            "label": "海口市",
            "value": 357
          }
        ]
      }
    ]
  }
]
